{
    "name": "lambda-builders",
    "resources": {},
    "language": {
        "csharp": {
            "packageReferences": {
                "Pulumi": "3.*",
                "Pulumi.Aws": "6.*"
            }
        },
        "go": {
            "generateResourceContainerTypes": true,
            "importBasePath": "github.com/pulumi/pulumi-lambda-builders/sdk/go/lambda-builders"
        },
        "nodejs": {
            "dependencies": {
                "@pulumi/aws": "^6.0.0"
            },
            "devDependencies": {
                "typescript": "^4.6.3"
            }
        },
        "python": {
            "requires": {
                "pulumi": ">=3.0.0,<4.0.0",
                "pulumi-aws": ">=6.0.0,<7.0.0"
            }
        }
    }
}
